{
  "$schema": "https://mono-ui.dev/schema/registry-item.json",
  "name": "data-table",
  "type": "registry:block",
  "title": "Data Table",
  "description": "A searchable, filterable data table with status badges and row actions.",
  "dependencies": [],
  "devDependencies": [],
  "registryDependencies": [
    "badge",
    "button",
    "input",
    "select",
    "table"
  ],
  "files": [
    {
      "path": "registry/radk/blocks/data-table.tsx",
      "type": "registry:component",
      "content": "\"use client\"\n\nimport * as React from \"react\"\nimport { Badge } from \"@/registry/radk/ui/badge\"\nimport { Button } from \"@/registry/radk/ui/button\"\nimport { Input } from \"@/registry/radk/ui/input\"\nimport {\n  Select,\n  SelectContent,\n  SelectItem,\n  SelectTrigger,\n  SelectValue,\n} from \"@/registry/radk/ui/select\"\nimport {\n  Table,\n  TableBody,\n  TableCell,\n  TableHead,\n  TableHeader,\n  TableRow,\n} from \"@/registry/radk/ui/table\"\n\ntype Status = \"active\" | \"inactive\" | \"pending\"\ntype BadgeVariant = \"default\" | \"secondary\" | \"outline\"\n\ninterface User {\n  name: string\n  email: string\n  role: string\n  status: Status\n  joined: string\n}\n\nconst users: User[] = [\n  { name: \"Alex Chen\", email: \"alex@example.com\", role: \"Admin\", status: \"active\", joined: \"Jan 2024\" },\n  { name: \"Maria Santos\", email: \"maria@example.com\", role: \"Member\", status: \"active\", joined: \"Feb 2024\" },\n  { name: \"James Park\", email: \"james@example.com\", role: \"Member\", status: \"inactive\", joined: \"Mar 2024\" },\n  { name: \"Sara Kim\", email: \"sara@example.com\", role: \"Editor\", status: \"active\", joined: \"Mar 2024\" },\n  { name: \"Tom Wilson\", email: \"tom@example.com\", role: \"Member\", status: \"pending\", joined: \"Apr 2024\" },\n  { name: \"Priya Nair\", email: \"priya@example.com\", role: \"Admin\", status: \"active\", joined: \"Apr 2024\" },\n]\n\nconst statusVariant: Record<Status, BadgeVariant> = {\n  active: \"default\",\n  inactive: \"secondary\",\n  pending: \"outline\",\n}\n\nexport function DataTableBlock() {\n  const [search, setSearch] = React.useState(\"\")\n  const [roleFilter, setRoleFilter] = React.useState(\"all\")\n\n  const filtered = users.filter(\n    (u) =>\n      (u.name.toLowerCase().includes(search.toLowerCase()) ||\n        u.email.toLowerCase().includes(search.toLowerCase())) &&\n      (roleFilter === \"all\" || u.role.toLowerCase() === roleFilter)\n  )\n\n  return (\n    <section className=\"py-10 px-6\">\n      <div className=\"mx-auto max-w-5xl space-y-4\">\n        <div className=\"flex items-center justify-between\">\n          <h2 className=\"text-xl font-black\">Team Members</h2>\n          <Button size=\"sm\">Add member</Button>\n        </div>\n        <div className=\"flex flex-col sm:flex-row items-stretch sm:items-center gap-3\">\n          <Input\n            placeholder=\"Search by name or email...\"\n            value={search}\n            onChange={(e) => setSearch(e.target.value)}\n            className=\"sm:max-w-xs\"\n          />\n          <Select value={roleFilter} onValueChange={setRoleFilter}>\n            <SelectTrigger className=\"w-full sm:w-36\">\n              <SelectValue placeholder=\"Filter by role\" />\n            </SelectTrigger>\n            <SelectContent>\n              <SelectItem value=\"all\">All roles</SelectItem>\n              <SelectItem value=\"admin\">Admin</SelectItem>\n              <SelectItem value=\"editor\">Editor</SelectItem>\n              <SelectItem value=\"member\">Member</SelectItem>\n            </SelectContent>\n          </Select>\n        </div>\n        <Table>\n          <TableHeader>\n            <TableRow>\n              <TableHead>Name</TableHead>\n              <TableHead>Role</TableHead>\n              <TableHead>Status</TableHead>\n              <TableHead>Joined</TableHead>\n              <TableHead className=\"text-right\">Actions</TableHead>\n            </TableRow>\n          </TableHeader>\n          <TableBody>\n            {filtered.map((user) => (\n              <TableRow key={user.email}>\n                <TableCell>\n                  <div className=\"font-medium\">{user.name}</div>\n                  <div className=\"text-xs text-muted-foreground\">\n                    {user.email}\n                  </div>\n                </TableCell>\n                <TableCell>{user.role}</TableCell>\n                <TableCell>\n                  <Badge variant={statusVariant[user.status]}>\n                    {user.status}\n                  </Badge>\n                </TableCell>\n                <TableCell className=\"text-muted-foreground\">\n                  {user.joined}\n                </TableCell>\n                <TableCell className=\"text-right\">\n                  <Button variant=\"ghost\" size=\"sm\">\n                    Edit\n                  </Button>\n                </TableCell>\n              </TableRow>\n            ))}\n          </TableBody>\n        </Table>\n        <p className=\"text-xs text-muted-foreground\">\n          Showing {filtered.length} of {users.length} members\n        </p>\n      </div>\n    </section>\n  )\n}\n"
    }
  ],
  "cssVars": {}
}
